laser/generic/SEIR.py
laser/generic/SEIRS.py
laser/generic/SI.py
laser/generic/SIR.py
laser/generic/SIRS.py
laser/generic/SIS.py
laser/generic/__init__.py
laser/generic/components.py
laser/generic/immunization.py
laser/generic/importation.py
laser/generic/model.py
laser/generic/shared.py
laser/generic/utils.py
laser/generic/vitaldynamics.py
laser_generic-1.0.0.dist-info/licenses/LICENSE
laser_generic-1.0.0.dist-info/METADATA
laser_generic-1.0.0.dist-info/WHEEL
laser_generic-1.0.0.dist-info/entry_points.txt
laser_generic-1.0.0.dist-info/top_level.txt
laser_generic-1.0.0.dist-info/RECORD
