Metadata-Version: 2.4
Name: laser.generic
Version: 1.0.0
Summary: Generic, SI/SIR/SEIR/etc., disease models implemented with the LASER toolkit.
Home-page: https://github.com/InstituteforDiseaseModeling/laser-generic
Author: Christopher Lorton
Author-email: Christopher Lorton <christopher.lorton@gatesfoundation.org>, Jonathan Bloedow <jonathan.bloedow@gatesfoundation.org>, Katherine Rosenfeld <katherine.rosenfeld@gatesfoundation.org>, Kevin McCarthy <kevin.mccarthy@gatesfoundation.org>, Paul R Saxman <paul.saxman@gatesfoundation.org>
Maintainer-email: Christopher Lorton <christopher.lorton@gatesfoundation.org>, Paul R Saxman <paul.saxman@gatesfoundation.org>
Project-URL: Homepage, https://github.com/InstituteforDiseaseModeling/laser-generic/
Project-URL: Documentation, https://institutefordiseasemodeling.github.io/laser-generic
Project-URL: Repository, https://github.com/InstituteforDiseaseModeling/laser-generic.git
Project-URL: Issues, https://github.com/InstituteforDiseaseModeling/laser-generic/issues
Project-URL: Changelog, https://github.com/InstituteforDiseaseModeling/laser-generic/blob/master/CHANGELOG.md
Keywords: sir,seir,spatial,modeling,laser
Classifier: Development Status :: 5 - Production/Stable
Classifier: Intended Audience :: Developers
Classifier: Operating System :: Unix
Classifier: Operating System :: POSIX
Classifier: Operating System :: Microsoft :: Windows
Classifier: Operating System :: MacOS
Classifier: Programming Language :: Python
Classifier: Programming Language :: Python :: 3
Classifier: Programming Language :: Python :: 3 :: Only
Classifier: Programming Language :: Python :: 3.9
Classifier: Programming Language :: Python :: 3.10
Classifier: Programming Language :: Python :: 3.11
Classifier: Programming Language :: Python :: 3.12
Classifier: Programming Language :: Python :: Implementation :: CPython
Classifier: Topic :: Utilities
Requires-Python: >=3.9
License-File: LICENSE
Requires-Dist: click
Requires-Dist: laser.core>=1.0.0
Requires-Dist: tqdm
Requires-Dist: geopandas
Requires-Dist: pandas
Requires-Dist: numpy
Requires-Dist: scipy
Requires-Dist: scikit-learn
Requires-Dist: mplcursors>=0.7
Requires-Dist: PyWavelets
Provides-Extra: dev
Requires-Dist: pre-commit; extra == "dev"
Requires-Dist: pytest; extra == "dev"
Provides-Extra: basemaps
Requires-Dist: contextily>=1.6.2; extra == "basemaps"
Dynamic: author
Dynamic: home-page
Dynamic: license-file
